reflex/__init__.py
reflex/__init__.pyi
reflex/__main__.py
reflex/admin.py
reflex/app.py
reflex/assets.py
reflex/base.py
reflex/config.py
reflex/environment.py
reflex/event.py
reflex/model.py
reflex/page.py
reflex/py.typed
reflex/reflex.py
reflex/route.py
reflex/state.py
reflex/style.py
reflex/testing.py
reflex/.templates/apps/blank/assets/favicon.ico
reflex/.templates/apps/blank/code/__init__.py
reflex/.templates/apps/blank/code/blank.py
reflex/.templates/web/.gitignore
reflex/.templates/web/jsconfig.json
reflex/.templates/web/postcss.config.js
reflex/.templates/web/react-router.config.js
reflex/.templates/web/vite-plugin-safari-cachebust.js
reflex/.templates/web/app/entry.client.js
reflex/.templates/web/app/routes.js
reflex/.templates/web/components/reflex/radix_themes_color_mode_provider.js
reflex/.templates/web/components/shiki/code.js
reflex/.templates/web/styles/__reflex_style_reset.css
reflex/.templates/web/utils/react-theme.js
reflex/.templates/web/utils/state.js
reflex/.templates/web/utils/helpers/dataeditor.js
reflex/.templates/web/utils/helpers/debounce.js
reflex/.templates/web/utils/helpers/paste.js
reflex/.templates/web/utils/helpers/range.js
reflex/.templates/web/utils/helpers/throttle.js
reflex/.templates/web/utils/helpers/upload.js
reflex/app_mixins/__init__.py
reflex/app_mixins/lifespan.py
reflex/app_mixins/middleware.py
reflex/app_mixins/mixin.py
reflex/compiler/__init__.py
reflex/compiler/compiler.py
reflex/compiler/templates.py
reflex/compiler/utils.py
reflex/components/__init__.py
reflex/components/__init__.pyi
reflex/components/component.py
reflex/components/dynamic.py
reflex/components/field.py
reflex/components/literals.py
reflex/components/props.py
reflex/components/base/__init__.py
reflex/components/base/__init__.pyi
reflex/components/base/app_wrap.py
reflex/components/base/app_wrap.pyi
reflex/components/base/bare.py
reflex/components/base/body.py
reflex/components/base/body.pyi
reflex/components/base/document.py
reflex-0.8.26.dist-info/METADATA
reflex-0.8.26.dist-info/WHEEL
reflex-0.8.26.dist-info/entry_points.txt
reflex-0.8.26.dist-info/licenses/LICENSE
reflex-0.8.26.dist-info/RECORD
