Metadata-Version: 2.4
Name: reflex
Version: 0.8.26
Summary: Web apps in pure Python.
Project-URL: homepage, https://reflex.dev
Project-URL: repository, https://github.com/reflex-dev/reflex
Project-URL: documentation, https://reflex.dev/docs/getting-started/introduction
Author: Nikhil Rao, Alek Petuskey, Masen Furer, Elijah Ahianyo, Thomas Brandeho, Khaleel Al-Adhami
Maintainer: Masen Furer, Khaleel Al-Adhami
Maintainer-email: maintainers@reflex.dev
License: Apache-2.0
License-File: LICENSE
Keywords: framework,web
Classifier: Development Status :: 4 - Beta
Classifier: License :: OSI Approved :: Apache Software License
Classifier: Programming Language :: Python :: 3
Classifier: Programming Language :: Python :: 3.10
Classifier: Programming Language :: Python :: 3.11
Classifier: Programming Language :: Python :: 3.12
Classifier: Programming Language :: Python :: 3.13
Classifier: Programming Language :: Python :: 3.14
Requires-Python: <4.0,>=3.10
Requires-Dist: alembic<2.0,>=1.15.2
Requires-Dist: click>=8.2
Requires-Dist: granian[reload]>=2.5.5
Requires-Dist: httpx<1.0,>=0.23.3
Requires-Dist: packaging<26,>=24.2
Requires-Dist: platformdirs<5.0,>=4.3.7
Requires-Dist: psutil<8.0,>=7.0.0; sys_platform == 'win32'
Requires-Dist: pydantic<3.0,>=1.10.21
Requires-Dist: python-multipart<1.0,>=0.0.20
Requires-Dist: python-socketio<6.0,>=5.12.0
Requires-Dist: redis<8.0,>=5.2.1
Requires-Dist: reflex-hosting-cli>=0.1.61
Requires-Dist: rich<15,>=13
Requires-Dist: sqlmodel<0.1,>=0.0.27
Requires-Dist: starlette>=0.47.0
Requires-Dist: typing-extensions>=4.13.0
Requires-Dist: wrapt<3.0,>=1.17.0
Provides-Extra: db
Requires-Dist: alembic<2.0,>=1.15.2; extra == 'db'
Requires-Dist: pydantic<3.0,>=1.10.21; extra == 'db'
Requires-Dist: sqlmodel<0.1,>=0.0.24; extra == 'db'
Provides-Extra: monitoring
Requires-Dist: pyleak<1.0,>=0.1.14; extra == 'monitoring'
